odoo/addons/sale_order_qty_change_no_recompute/README.rst
odoo/addons/sale_order_qty_change_no_recompute/__init__.py
odoo/addons/sale_order_qty_change_no_recompute/__manifest__.py
odoo/addons/sale_order_qty_change_no_recompute/i18n/sale_order_qty_change_no_recompute.pot
odoo/addons/sale_order_qty_change_no_recompute/models/__init__.py
odoo/addons/sale_order_qty_change_no_recompute/models/sale_order.py
odoo/addons/sale_order_qty_change_no_recompute/readme/CONTRIBUTORS.rst
odoo/addons/sale_order_qty_change_no_recompute/readme/DESCRIPTION.rst
odoo/addons/sale_order_qty_change_no_recompute/readme/USAGE.rst
odoo/addons/sale_order_qty_change_no_recompute/static/description/icon.png
odoo/addons/sale_order_qty_change_no_recompute/static/description/index.html
odoo/addons/sale_order_qty_change_no_recompute/tests/__init__.py
odoo/addons/sale_order_qty_change_no_recompute/tests/test_sale_order_qty_change.py
odoo12_addon_sale_order_qty_change_no_recompute-12.0.1.0.1.dist-info/METADATA
odoo12_addon_sale_order_qty_change_no_recompute-12.0.1.0.1.dist-info/WHEEL
odoo12_addon_sale_order_qty_change_no_recompute-12.0.1.0.1.dist-info/top_level.txt
odoo12_addon_sale_order_qty_change_no_recompute-12.0.1.0.1.dist-info/RECORD
